parze/__init__.py
parze/parze.py
parze-0.2.2.dist-info/licenses/LICENSE
parze-0.2.2.dist-info/METADATA
parze-0.2.2.dist-info/WHEEL
parze-0.2.2.dist-info/top_level.txt
parze-0.2.2.dist-info/RECORD
