Metadata-Version: 2.4
Name: parze
Version: 0.2.2
Summary: Python SDK for the Parze API
Author: gideononyewuenyi
License: MIT License
Project-URL: Homepage, https://platform.parze.ai
Keywords: parze,sdk,document-processing,api
Classifier: Programming Language :: Python :: 3
Classifier: Programming Language :: Python :: 3 :: Only
Classifier: Programming Language :: Python :: 3.7
Classifier: License :: OSI Approved :: MIT License
Classifier: Operating System :: OS Independent
Classifier: Intended Audience :: Developers
Classifier: Topic :: Software Development :: Libraries :: Python Modules
Requires-Python: >=3.7
License-File: LICENSE
Requires-Dist: requests>=2.31
Dynamic: license-file
